{
  "custom": {},
  "params": {},
  "permissions": {
    "securityLevels": [
      {
        "children": [],
        "name": "Authenticated"
      }
    ],
    "type": "AnyOf"
  },
  "props": {
    "defaultSize": {
      "height": 818
    }
  },
  "root": {
    "children": [
      {
        "meta": {
          "name": "SubHeaderEmbedded"
        },
        "position": {
          "basis": "32px",
          "shrink": 0
        },
        "props": {
          "params": {
            "icon": "settings",
            "text": "Maintain CIP Circuits"
          },
          "path": "CORE_V/Headers/SubHeader"
        },
        "type": "ia.display.view"
      },
      {
        "meta": {
          "name": "CurrentSite"
        },
        "position": {
          "basis": "0px",
          "display": false,
          "shrink": 0
        },
        "props": {
          "params": {
            "site": null,
            "site_id": null
          },
          "path": "CORE_V/Utils/CurrentSite"
        },
        "type": "ia.display.view"
      },
      {
        "children": [
          {
            "events": {
              "dom": {
                "onClick": {
                  "config": {
                    "script": "\t\t\n\t# Make sure we have edit permission to do this\n\tif (not CORE_P.User.hasPermission(self, Constants_P.PROJECT[\u0027project_name\u0027], \u0027SITEADMIN\u0027)):\n\t\treturn\n\t\t\t\n\t# Opens a popup view. We are passing in two parameters, called \"myParam\" and \"myParam2\". We also set some additional properties of the popup.\n\tsystem.perspective.openPopup(\"CircuitAddEdit\",\n\t\t\t\t\t\t\t\t  \u0027CIP_V/Administration/Circuit/AddEdit\u0027, \n\t\t\t\t\t\t\t\t  params \u003d {\u0027id\u0027:\t\t\t\t\t\t\u0027\u0027,\n  \t\t\t\t\t\t\t\t  \t\t\t\u0027site_id\u0027:\t\t\t\t\tself.parent.parent.getChild(\"CurrentSite\").props.params.site_id,\n  \t\t\t\t\t\t\t\t  \t\t\t\u0027system_id\u0027:\t\t\t\t\u0027\u0027,\n  \t\t\t\t\t\t\t\t  \t\t\t\u0027system_name\u0027:\t\t\t\t\u0027\u0027,\n  \t\t\t\t\t\t\t\t  \t\t\t\u0027line_id\u0027:\t\t\t\t\t\u0027\u0027,\n  \t\t\t\t\t\t\t\t  \t\t\t\u0027line_name\u0027:\t\t\t\t\u0027\u0027,\n\t\t\t\t\t\t\t\t  \t\t\t\u0027step_number\u0027:\t\t\t\t\u0027\u0027,\n\t\t\t\t\t\t\t\t  \t\t\t\u0027step_type_id\u0027:\t\t\t\t\u0027\u0027,\n\t\t\t\t\t\t\t\t  \t\t\t\u0027circuit_name\u0027:\t\t\t\t\u0027\u0027,\n\t\t\t\t\t\t\t\t  \t\t\t\u0027circuit_description\u0027:\t\t\u0027\u0027,\n  \t\t\t\t\t\t\t\t  \t\t\t\u0027state_idle\u0027:\t\t\t\t\u0027\u0027,\n  \t\t\t\t\t\t\t\t  \t\t\t\u0027state_running\u0027:\t\t\t\u0027\u0027,\n  \t\t\t\t\t\t\t\t  \t\t\t\u0027state_held\u0027:\t\t\t\t\u0027\u0027,\n  \t\t\t\t\t\t\t\t  \t\t\t\u0027state_completed\u0027:\t\t\t\u0027\u0027,\n  \t\t\t\t\t\t\t\t  \t\t\t\u0027state_stopped\u0027:\t\t\t\u0027\u0027,\n  \t\t\t\t\t\t\t\t  \t\t\t\u0027state_pasued\u0027:\t\t\t\t\u0027\u0027,\n    \t\t\t\t\t\t\t\t  \t\t\u0027edit\u0027:\t\t\t\t\t\tFalse,\n    \t\t\t\t\t\t\t\t  \t\t\t}, \n\t\t\t\t\t\t\t\t  showCloseIcon \u003d True, \n\t\t\t\t\t\t\t\t  title \u003d \u0027Add CIP Circuit\u0027, \n\t\t\t\t\t\t\t\t  modal \u003d True)\t"
                  },
                  "scope": "G",
                  "type": "script"
                }
              }
            },
            "meta": {
              "name": "AddCircuitButton"
            },
            "position": {
              "basis": "200px",
              "shrink": 0
            },
            "propConfig": {
              "custom.selected_plant_id": {
                "persistent": false
              },
              "props.enabled": {
                "binding": {
                  "config": {
                    "struct": {
                      "site_id": "{../CurrentSite.props.params.site_id}",
                      "username": "{session.props.auth.user.userName}"
                    },
                    "waitOnAll": true
                  },
                  "transforms": [
                    {
                      "code": "\treturn CORE_P.User.hasPermission(self, Constants_P.PROJECT[\u0027project_name\u0027], \u0027SITEADMIN\u0027)\n\t\t\n\t",
                      "type": "script"
                    }
                  ],
                  "type": "expr-struct"
                }
              }
            },
            "props": {
              "text": "Add New Circuit"
            },
            "type": "ia.input.button"
          }
        ],
        "meta": {
          "name": "TopContainer"
        },
        "position": {
          "basis": "32px"
        },
        "props": {
          "alignContent": "flex-end",
          "alignItems": "center",
          "justify": "flex-end",
          "style": {
            "marginBottom": 1,
            "marginLeft": 4,
            "marginRight": 4,
            "overflow": "hidden"
          }
        },
        "type": "ia.container.flex"
      },
      {
        "events": {
          "component": {
            "onRowDoubleClick": {
              "config": {
                "script": "\t\n\ttry:\n\t\n\t\t# Make sure we have edit permission to do this\n\t\tif (not CORE_P.User.hasPermission(self, Constants_P.PROJECT[\u0027project_name\u0027], \u0027SITEADMIN\u0027)):\n\t\t\tCORE_P.Utils.errorPopup(\"You don\u0027t have sufficent user rights\")\n\t\t\treturn\n\t\t\t\t\n\t\t# Opens a popup view. We are passing in two parameters, called \"myParam\" and \"myParam2\". We also set some additional properties of the popup.\n\t\tsystem.perspective.openPopup(\"CircuitAddEdit\",\n\t\t\t\t\t\t\t\t\t  \u0027CIP_V/Administration/Circuit/AddEdit\u0027, \n\t\t\t\t\t\t\t\t\t  params \u003d {\u0027id\u0027:\t\t\t\t\tevent.value[\u0027id\u0027],\n\t\t\t\t\t\t\t\t\t  \t\t\t\u0027site_id\u0027:\t\t\t\tself.getSibling(\"CurrentSite\").props.params.site_id,\n\t\t\t\t\t\t\t\t\t  \t\t\t\u0027system_id\u0027:\t\t\tevent.value[\u0027system_id\u0027],\n\t\t\t\t\t\t\t\t\t  \t\t\t\u0027system_name\u0027:\t\t\tevent.value[\u0027system_name\u0027],\n\t\t\t\t\t\t\t\t\t  \t\t\t\u0027line_id\u0027:\t\t\t\tevent.value[\u0027line_id\u0027],\n\t\t\t\t\t\t\t\t\t  \t\t\t\u0027line_name\u0027:\t\t\tevent.value[\u0027line_name\u0027],\n\t  \t\t\t\t\t\t\t\t  \t\t\t\u0027step_number\u0027:\t\t\tevent.value[\u0027step_number\u0027],\n\t  \t\t\t\t\t\t\t\t  \t\t\t\u0027step_type_id\u0027:\t\t\tevent.value[\u0027step_type_id\u0027],\n\t  \t\t\t\t\t\t\t\t  \t\t\t\u0027circuit_name\u0027:\t\t\tevent.value[\u0027name\u0027],\n\t  \t\t\t\t\t\t\t\t  \t\t\t\u0027circuit_description\u0027:\tevent.value[\u0027description\u0027],\n\t  \t\t\t\t\t\t\t\t  \t\t\t\u0027state_idle\u0027:\t\t\tevent.value[\u0027state_idle\u0027],\n\t  \t\t\t\t\t\t\t\t  \t\t\t\u0027state_running\u0027:\t\tevent.value[\u0027state_running\u0027],\n\t  \t\t\t\t\t\t\t\t  \t\t\t\u0027state_held\u0027:\t\t\tevent.value[\u0027state_held\u0027],\n\t  \t\t\t\t\t\t\t\t  \t\t\t\u0027state_completed\u0027:\t\tevent.value[\u0027state_completed\u0027],\n\t  \t\t\t\t\t\t\t\t  \t\t\t\u0027state_stopped\u0027:\t\tevent.value[\u0027state_stopped\u0027],\n\t  \t\t\t\t\t\t\t\t  \t\t\t\u0027state_paused\u0027:\t\t\tevent.value[\u0027state_paused\u0027],\n\t  \t\t\t\t\t\t\t\t  \t\t\t\u0027edit\u0027:\t\t\t\t\tTrue,\n\t  \t\t\t\t\t\t\t\t  \t\t\t\u0027updated_by\u0027: \t\t\tself.session.props.auth.user.userName,\n\t  \t\t\t\t\t\t\t\t  \t\t\t}, \n\t\t\t\t\t\t\t\t\t  showCloseIcon \u003d True, \n\t\t\t\t\t\t\t\t\t  title \u003d \u0027Edit Exisiting CIP Circuit\u0027, \n\t\t\t\t\t\t\t\t\t  modal \u003d True)\t\n\texcept:\n\t\tCORE_P.Utils.errorPopup(\u0027Error:\u0027)"
              },
              "scope": "G",
              "type": "script"
            }
          }
        },
        "meta": {
          "name": "Table"
        },
        "position": {
          "basis": "423px",
          "grow": 1
        },
        "propConfig": {
          "meta.visible": {
            "binding": {
              "config": {
                "struct": {
                  "site_id": "{../CurrentSite.props.params.site_id}",
                  "username": "{session.props.auth.user.userName}"
                },
                "waitOnAll": true
              },
              "transforms": [
                {
                  "code": "\treturn CORE_P.User.hasPermission(self, Constants_P.PROJECT[\u0027project_name\u0027], \u0027SITEADMIN\u0027)\n\t\t\n\t",
                  "type": "script"
                }
              ],
              "type": "expr-struct"
            }
          },
          "props.data": {
            "binding": {
              "config": {
                "parameters": {
                  "site_id": "{../CurrentSite.props.params.site_id}"
                },
                "queryPath": "CIP_Q/DB_Query/Get_CIP_Circuit",
                "returnFormat": "json"
              },
              "type": "query"
            }
          }
        },
        "props": {
          "columns": [
            {
              "align": "center",
              "boolean": "checkbox",
              "dateFormat": "MM/DD/YYYY",
              "editable": false,
              "field": "system_name",
              "filter": {
                "boolean": {
                  "condition": ""
                },
                "date": {
                  "condition": "",
                  "value": ""
                },
                "enabled": false,
                "number": {
                  "condition": "",
                  "value": ""
                },
                "string": {
                  "condition": "",
                  "value": ""
                },
                "visible": "on-hover"
              },
              "footer": {
                "align": "center",
                "justify": "left",
                "style": {
                  "classes": ""
                },
                "title": ""
              },
              "header": {
                "align": "center",
                "justify": "center",
                "style": {
                  "classes": ""
                },
                "title": "System"
              },
              "justify": "center",
              "nullFormat": {
                "includeNullStrings": false,
                "nullFormatValue": "",
                "strict": false
              },
              "number": "value",
              "numberFormat": "0,0.##",
              "progressBar": {
                "bar": {
                  "color": "",
                  "style": {
                    "classes": ""
                  }
                },
                "max": 100,
                "min": 0,
                "track": {
                  "color": "",
                  "style": {
                    "classes": ""
                  }
                },
                "value": {
                  "enabled": true,
                  "format": "0,0.##",
                  "justify": "center",
                  "style": {
                    "classes": ""
                  }
                }
              },
              "render": "auto",
              "resizable": true,
              "sort": "ascending",
              "sortable": true,
              "strictWidth": false,
              "style": {
                "classes": ""
              },
              "toggleSwitch": {
                "color": {
                  "selected": "",
                  "unselected": ""
                }
              },
              "viewParams": {},
              "viewPath": "",
              "visible": true,
              "width": ""
            },
            {
              "align": "center",
              "boolean": "checkbox",
              "dateFormat": "MM/DD/YYYY",
              "editable": false,
              "field": "line_name",
              "filter": {
                "boolean": {
                  "condition": ""
                },
                "date": {
                  "condition": "",
                  "value": ""
                },
                "enabled": false,
                "number": {
                  "condition": "",
                  "value": ""
                },
                "string": {
                  "condition": "",
                  "value": ""
                },
                "visible": "on-hover"
              },
              "footer": {
                "align": "center",
                "justify": "left",
                "style": {
                  "classes": ""
                },
                "title": ""
              },
              "header": {
                "align": "center",
                "justify": "center",
                "style": {
                  "classes": ""
                },
                "title": "Line"
              },
              "justify": "center",
              "nullFormat": {
                "includeNullStrings": false,
                "nullFormatValue": "",
                "strict": false
              },
              "number": "value",
              "numberFormat": "0,0.##",
              "progressBar": {
                "bar": {
                  "color": "",
                  "style": {
                    "classes": ""
                  }
                },
                "max": 100,
                "min": 0,
                "track": {
                  "color": "",
                  "style": {
                    "classes": ""
                  }
                },
                "value": {
                  "enabled": true,
                  "format": "0,0.##",
                  "justify": "center",
                  "style": {
                    "classes": ""
                  }
                }
              },
              "render": "auto",
              "resizable": true,
              "sort": "none",
              "sortable": true,
              "strictWidth": false,
              "style": {
                "classes": ""
              },
              "toggleSwitch": {
                "color": {
                  "selected": "",
                  "unselected": ""
                }
              },
              "viewParams": {},
              "viewPath": "",
              "visible": true,
              "width": ""
            },
            {
              "align": "center",
              "boolean": "checkbox",
              "dateFormat": "MM/DD/YYYY",
              "editable": false,
              "field": "name",
              "filter": {
                "boolean": {
                  "condition": ""
                },
                "date": {
                  "condition": "",
                  "value": ""
                },
                "enabled": false,
                "number": {
                  "condition": "",
                  "value": ""
                },
                "string": {
                  "condition": "",
                  "value": ""
                },
                "visible": "on-hover"
              },
              "footer": {
                "align": "center",
                "justify": "left",
                "style": {
                  "classes": ""
                },
                "title": ""
              },
              "header": {
                "align": "center",
                "justify": "center",
                "style": {
                  "classes": ""
                },
                "title": "Name"
              },
              "justify": "center",
              "nullFormat": {
                "includeNullStrings": false,
                "nullFormatValue": "",
                "strict": false
              },
              "number": "value",
              "numberFormat": "0,0.##",
              "progressBar": {
                "bar": {
                  "color": "",
                  "style": {
                    "classes": ""
                  }
                },
                "max": 100,
                "min": 0,
                "track": {
                  "color": "",
                  "style": {
                    "classes": ""
                  }
                },
                "value": {
                  "enabled": true,
                  "format": "0,0.##",
                  "justify": "center",
                  "style": {
                    "classes": ""
                  }
                }
              },
              "render": "auto",
              "resizable": true,
              "sort": "none",
              "sortable": true,
              "strictWidth": false,
              "style": {
                "classes": ""
              },
              "toggleSwitch": {
                "color": {
                  "selected": "",
                  "unselected": ""
                }
              },
              "viewParams": {},
              "viewPath": "",
              "visible": true,
              "width": ""
            },
            {
              "align": "center",
              "boolean": "checkbox",
              "dateFormat": "MM/DD/YYYY",
              "editable": false,
              "field": "description",
              "filter": {
                "boolean": {
                  "condition": ""
                },
                "date": {
                  "condition": "",
                  "value": ""
                },
                "enabled": false,
                "number": {
                  "condition": "",
                  "value": ""
                },
                "string": {
                  "condition": "",
                  "value": ""
                },
                "visible": "on-hover"
              },
              "footer": {
                "align": "center",
                "justify": "left",
                "style": {
                  "classes": ""
                },
                "title": ""
              },
              "header": {
                "align": "center",
                "justify": "center",
                "style": {
                  "classes": ""
                },
                "title": "Description"
              },
              "justify": "center",
              "nullFormat": {
                "includeNullStrings": false,
                "nullFormatValue": "",
                "strict": false
              },
              "number": "value",
              "numberFormat": "0,0.##",
              "progressBar": {
                "bar": {
                  "color": "",
                  "style": {
                    "classes": ""
                  }
                },
                "max": 100,
                "min": 0,
                "track": {
                  "color": "",
                  "style": {
                    "classes": ""
                  }
                },
                "value": {
                  "enabled": true,
                  "format": "0,0.##",
                  "justify": "center",
                  "style": {
                    "classes": ""
                  }
                }
              },
              "render": "auto",
              "resizable": true,
              "sort": "none",
              "sortable": true,
              "strictWidth": false,
              "style": {
                "classes": ""
              },
              "toggleSwitch": {
                "color": {
                  "selected": "",
                  "unselected": ""
                }
              },
              "viewParams": {},
              "viewPath": "",
              "visible": true,
              "width": ""
            },
            {
              "align": "center",
              "boolean": "checkbox",
              "dateFormat": "MM/DD/YYYY",
              "editable": false,
              "field": "",
              "filter": {
                "boolean": {
                  "condition": ""
                },
                "date": {
                  "condition": "",
                  "value": ""
                },
                "enabled": false,
                "number": {
                  "condition": "",
                  "value": ""
                },
                "string": {
                  "condition": "",
                  "value": ""
                },
                "visible": "on-hover"
              },
              "footer": {
                "align": "center",
                "justify": "left",
                "style": {
                  "classes": ""
                },
                "title": ""
              },
              "header": {
                "align": "center",
                "justify": "left",
                "style": {
                  "classes": ""
                },
                "title": ""
              },
              "justify": "auto",
              "nullFormat": {
                "includeNullStrings": false,
                "nullFormatValue": "",
                "strict": false
              },
              "number": "value",
              "numberFormat": "0,0.##",
              "progressBar": {
                "bar": {
                  "color": "",
                  "style": {
                    "classes": ""
                  }
                },
                "max": 100,
                "min": 0,
                "track": {
                  "color": "",
                  "style": {
                    "classes": ""
                  }
                },
                "value": {
                  "enabled": true,
                  "format": "0,0.##",
                  "justify": "center",
                  "style": {
                    "classes": ""
                  }
                }
              },
              "render": "auto",
              "resizable": true,
              "sort": "none",
              "sortable": true,
              "strictWidth": false,
              "style": {
                "classes": ""
              },
              "toggleSwitch": {
                "color": {
                  "selected": "",
                  "unselected": ""
                }
              },
              "viewParams": {},
              "viewPath": "",
              "visible": false,
              "width": ""
            },
            {
              "align": "center",
              "boolean": "checkbox",
              "dateFormat": "MM/DD/YYYY",
              "editable": false,
              "field": "",
              "filter": {
                "boolean": {
                  "condition": ""
                },
                "date": {
                  "condition": "",
                  "value": ""
                },
                "enabled": false,
                "number": {
                  "condition": "",
                  "value": ""
                },
                "string": {
                  "condition": "",
                  "value": ""
                },
                "visible": "on-hover"
              },
              "footer": {
                "align": "center",
                "justify": "left",
                "style": {
                  "classes": ""
                },
                "title": ""
              },
              "header": {
                "align": "center",
                "justify": "left",
                "style": {
                  "classes": ""
                },
                "title": ""
              },
              "justify": "auto",
              "nullFormat": {
                "includeNullStrings": false,
                "nullFormatValue": "",
                "strict": false
              },
              "number": "value",
              "numberFormat": "0,0.##",
              "progressBar": {
                "bar": {
                  "color": "",
                  "style": {
                    "classes": ""
                  }
                },
                "max": 100,
                "min": 0,
                "track": {
                  "color": "",
                  "style": {
                    "classes": ""
                  }
                },
                "value": {
                  "enabled": true,
                  "format": "0,0.##",
                  "justify": "center",
                  "style": {
                    "classes": ""
                  }
                }
              },
              "render": "auto",
              "resizable": true,
              "sort": "none",
              "sortable": true,
              "strictWidth": false,
              "style": {
                "classes": ""
              },
              "toggleSwitch": {
                "color": {
                  "selected": "",
                  "unselected": ""
                }
              },
              "viewParams": {},
              "viewPath": "",
              "visible": false,
              "width": ""
            },
            {
              "align": "center",
              "boolean": "checkbox",
              "dateFormat": "MM/DD/YYYY",
              "editable": false,
              "field": "",
              "filter": {
                "boolean": {
                  "condition": ""
                },
                "date": {
                  "condition": "",
                  "value": ""
                },
                "enabled": false,
                "number": {
                  "condition": "",
                  "value": ""
                },
                "string": {
                  "condition": "",
                  "value": ""
                },
                "visible": "on-hover"
              },
              "footer": {
                "align": "center",
                "justify": "left",
                "style": {
                  "classes": ""
                },
                "title": ""
              },
              "header": {
                "align": "center",
                "justify": "left",
                "style": {
                  "classes": ""
                },
                "title": ""
              },
              "justify": "auto",
              "nullFormat": {
                "includeNullStrings": false,
                "nullFormatValue": "",
                "strict": false
              },
              "number": "value",
              "numberFormat": "0,0.##",
              "progressBar": {
                "bar": {
                  "color": "",
                  "style": {
                    "classes": ""
                  }
                },
                "max": 100,
                "min": 0,
                "track": {
                  "color": "",
                  "style": {
                    "classes": ""
                  }
                },
                "value": {
                  "enabled": true,
                  "format": "0,0.##",
                  "justify": "center",
                  "style": {
                    "classes": ""
                  }
                }
              },
              "render": "auto",
              "resizable": true,
              "sort": "none",
              "sortable": true,
              "strictWidth": false,
              "style": {
                "classes": ""
              },
              "toggleSwitch": {
                "color": {
                  "selected": "",
                  "unselected": ""
                }
              },
              "viewParams": {},
              "viewPath": "",
              "visible": false,
              "width": ""
            },
            {
              "align": "center",
              "boolean": "checkbox",
              "dateFormat": "MM/DD/YYYY",
              "editable": false,
              "field": "",
              "filter": {
                "boolean": {
                  "condition": ""
                },
                "date": {
                  "condition": "",
                  "value": ""
                },
                "enabled": false,
                "number": {
                  "condition": "",
                  "value": ""
                },
                "string": {
                  "condition": "",
                  "value": ""
                },
                "visible": "on-hover"
              },
              "footer": {
                "align": "center",
                "justify": "left",
                "style": {
                  "classes": ""
                },
                "title": ""
              },
              "header": {
                "align": "center",
                "justify": "left",
                "style": {
                  "classes": ""
                },
                "title": ""
              },
              "justify": "auto",
              "nullFormat": {
                "includeNullStrings": false,
                "nullFormatValue": "",
                "strict": false
              },
              "number": "value",
              "numberFormat": "0,0.##",
              "progressBar": {
                "bar": {
                  "color": "",
                  "style": {
                    "classes": ""
                  }
                },
                "max": 100,
                "min": 0,
                "track": {
                  "color": "",
                  "style": {
                    "classes": ""
                  }
                },
                "value": {
                  "enabled": true,
                  "format": "0,0.##",
                  "justify": "center",
                  "style": {
                    "classes": ""
                  }
                }
              },
              "render": "auto",
              "resizable": true,
              "sort": "none",
              "sortable": true,
              "strictWidth": false,
              "style": {
                "classes": ""
              },
              "toggleSwitch": {
                "color": {
                  "selected": "",
                  "unselected": ""
                }
              },
              "viewParams": {},
              "viewPath": "",
              "visible": false,
              "width": ""
            },
            {
              "align": "center",
              "boolean": "checkbox",
              "dateFormat": "MM/DD/YYYY",
              "editable": false,
              "field": "",
              "filter": {
                "boolean": {
                  "condition": ""
                },
                "date": {
                  "condition": "",
                  "value": ""
                },
                "enabled": false,
                "number": {
                  "condition": "",
                  "value": ""
                },
                "string": {
                  "condition": "",
                  "value": ""
                },
                "visible": "on-hover"
              },
              "footer": {
                "align": "center",
                "justify": "left",
                "style": {
                  "classes": ""
                },
                "title": ""
              },
              "header": {
                "align": "center",
                "justify": "left",
                "style": {
                  "classes": ""
                },
                "title": ""
              },
              "justify": "auto",
              "nullFormat": {
                "includeNullStrings": false,
                "nullFormatValue": "",
                "strict": false
              },
              "number": "value",
              "numberFormat": "0,0.##",
              "progressBar": {
                "bar": {
                  "color": "",
                  "style": {
                    "classes": ""
                  }
                },
                "max": 100,
                "min": 0,
                "track": {
                  "color": "",
                  "style": {
                    "classes": ""
                  }
                },
                "value": {
                  "enabled": true,
                  "format": "0,0.##",
                  "justify": "center",
                  "style": {
                    "classes": ""
                  }
                }
              },
              "render": "auto",
              "resizable": true,
              "sort": "none",
              "sortable": true,
              "strictWidth": false,
              "style": {
                "classes": ""
              },
              "toggleSwitch": {
                "color": {
                  "selected": "",
                  "unselected": ""
                }
              },
              "viewParams": {},
              "viewPath": "",
              "visible": false,
              "width": ""
            },
            {
              "align": "center",
              "boolean": "checkbox",
              "dateFormat": "MM/DD/YYYY",
              "editable": false,
              "field": "",
              "filter": {
                "boolean": {
                  "condition": ""
                },
                "date": {
                  "condition": "",
                  "value": ""
                },
                "enabled": false,
                "number": {
                  "condition": "",
                  "value": ""
                },
                "string": {
                  "condition": "",
                  "value": ""
                },
                "visible": "on-hover"
              },
              "footer": {
                "align": "center",
                "justify": "left",
                "style": {
                  "classes": ""
                },
                "title": ""
              },
              "header": {
                "align": "center",
                "justify": "left",
                "style": {
                  "classes": ""
                },
                "title": ""
              },
              "justify": "auto",
              "nullFormat": {
                "includeNullStrings": false,
                "nullFormatValue": "",
                "strict": false
              },
              "number": "value",
              "numberFormat": "0,0.##",
              "progressBar": {
                "bar": {
                  "color": "",
                  "style": {
                    "classes": ""
                  }
                },
                "max": 100,
                "min": 0,
                "track": {
                  "color": "",
                  "style": {
                    "classes": ""
                  }
                },
                "value": {
                  "enabled": true,
                  "format": "0,0.##",
                  "justify": "center",
                  "style": {
                    "classes": ""
                  }
                }
              },
              "render": "auto",
              "resizable": true,
              "sort": "none",
              "sortable": true,
              "strictWidth": false,
              "style": {
                "classes": ""
              },
              "toggleSwitch": {
                "color": {
                  "selected": "",
                  "unselected": ""
                }
              },
              "viewParams": {},
              "viewPath": "",
              "visible": false,
              "width": ""
            },
            {
              "align": "center",
              "boolean": "checkbox",
              "dateFormat": "MM/DD/YYYY",
              "editable": false,
              "field": "",
              "filter": {
                "boolean": {
                  "condition": ""
                },
                "date": {
                  "condition": "",
                  "value": ""
                },
                "enabled": false,
                "number": {
                  "condition": "",
                  "value": ""
                },
                "string": {
                  "condition": "",
                  "value": ""
                },
                "visible": "on-hover"
              },
              "footer": {
                "align": "center",
                "justify": "left",
                "style": {
                  "classes": ""
                },
                "title": ""
              },
              "header": {
                "align": "center",
                "justify": "left",
                "style": {
                  "classes": ""
                },
                "title": ""
              },
              "justify": "auto",
              "nullFormat": {
                "includeNullStrings": false,
                "nullFormatValue": "",
                "strict": false
              },
              "number": "value",
              "numberFormat": "0,0.##",
              "progressBar": {
                "bar": {
                  "color": "",
                  "style": {
                    "classes": ""
                  }
                },
                "max": 100,
                "min": 0,
                "track": {
                  "color": "",
                  "style": {
                    "classes": ""
                  }
                },
                "value": {
                  "enabled": true,
                  "format": "0,0.##",
                  "justify": "center",
                  "style": {
                    "classes": ""
                  }
                }
              },
              "render": "auto",
              "resizable": true,
              "sort": "none",
              "sortable": true,
              "strictWidth": false,
              "style": {
                "classes": ""
              },
              "toggleSwitch": {
                "color": {
                  "selected": "",
                  "unselected": ""
                }
              },
              "viewParams": {},
              "viewPath": "",
              "visible": false,
              "width": ""
            },
            {
              "align": "center",
              "boolean": "checkbox",
              "dateFormat": "MM/DD/YYYY",
              "editable": false,
              "field": "",
              "filter": {
                "boolean": {
                  "condition": ""
                },
                "date": {
                  "condition": "",
                  "value": ""
                },
                "enabled": false,
                "number": {
                  "condition": "",
                  "value": ""
                },
                "string": {
                  "condition": "",
                  "value": ""
                },
                "visible": "on-hover"
              },
              "footer": {
                "align": "center",
                "justify": "left",
                "style": {
                  "classes": ""
                },
                "title": ""
              },
              "header": {
                "align": "center",
                "justify": "left",
                "style": {
                  "classes": ""
                },
                "title": ""
              },
              "justify": "auto",
              "nullFormat": {
                "includeNullStrings": false,
                "nullFormatValue": "",
                "strict": false
              },
              "number": "value",
              "numberFormat": "0,0.##",
              "progressBar": {
                "bar": {
                  "color": "",
                  "style": {
                    "classes": ""
                  }
                },
                "max": 100,
                "min": 0,
                "track": {
                  "color": "",
                  "style": {
                    "classes": ""
                  }
                },
                "value": {
                  "enabled": true,
                  "format": "0,0.##",
                  "justify": "center",
                  "style": {
                    "classes": ""
                  }
                }
              },
              "render": "auto",
              "resizable": true,
              "sort": "none",
              "sortable": true,
              "strictWidth": false,
              "style": {
                "classes": ""
              },
              "toggleSwitch": {
                "color": {
                  "selected": "",
                  "unselected": ""
                }
              },
              "viewParams": {},
              "viewPath": "",
              "visible": false,
              "width": ""
            },
            {
              "align": "center",
              "boolean": "checkbox",
              "dateFormat": "MM/DD/YYYY",
              "editable": false,
              "field": "",
              "filter": {
                "boolean": {
                  "condition": ""
                },
                "date": {
                  "condition": "",
                  "value": ""
                },
                "enabled": false,
                "number": {
                  "condition": "",
                  "value": ""
                },
                "string": {
                  "condition": "",
                  "value": ""
                },
                "visible": "on-hover"
              },
              "footer": {
                "align": "center",
                "justify": "left",
                "style": {
                  "classes": ""
                },
                "title": ""
              },
              "header": {
                "align": "center",
                "justify": "left",
                "style": {
                  "classes": ""
                },
                "title": ""
              },
              "justify": "auto",
              "nullFormat": {
                "includeNullStrings": false,
                "nullFormatValue": "",
                "strict": false
              },
              "number": "value",
              "numberFormat": "0,0.##",
              "progressBar": {
                "bar": {
                  "color": "",
                  "style": {
                    "classes": ""
                  }
                },
                "max": 100,
                "min": 0,
                "track": {
                  "color": "",
                  "style": {
                    "classes": ""
                  }
                },
                "value": {
                  "enabled": true,
                  "format": "0,0.##",
                  "justify": "center",
                  "style": {
                    "classes": ""
                  }
                }
              },
              "render": "auto",
              "resizable": true,
              "sort": "none",
              "sortable": true,
              "strictWidth": false,
              "style": {
                "classes": ""
              },
              "toggleSwitch": {
                "color": {
                  "selected": "",
                  "unselected": ""
                }
              },
              "viewParams": {},
              "viewPath": "",
              "visible": false,
              "width": ""
            },
            {
              "align": "center",
              "boolean": "checkbox",
              "dateFormat": "MM/DD/YYYY",
              "editable": false,
              "field": "",
              "filter": {
                "boolean": {
                  "condition": ""
                },
                "date": {
                  "condition": "",
                  "value": ""
                },
                "enabled": false,
                "number": {
                  "condition": "",
                  "value": ""
                },
                "string": {
                  "condition": "",
                  "value": ""
                },
                "visible": "on-hover"
              },
              "footer": {
                "align": "center",
                "justify": "left",
                "style": {
                  "classes": ""
                },
                "title": ""
              },
              "header": {
                "align": "center",
                "justify": "left",
                "style": {
                  "classes": ""
                },
                "title": ""
              },
              "justify": "auto",
              "nullFormat": {
                "includeNullStrings": false,
                "nullFormatValue": "",
                "strict": false
              },
              "number": "value",
              "numberFormat": "0,0.##",
              "progressBar": {
                "bar": {
                  "color": "",
                  "style": {
                    "classes": ""
                  }
                },
                "max": 100,
                "min": 0,
                "track": {
                  "color": "",
                  "style": {
                    "classes": ""
                  }
                },
                "value": {
                  "enabled": true,
                  "format": "0,0.##",
                  "justify": "center",
                  "style": {
                    "classes": ""
                  }
                }
              },
              "render": "auto",
              "resizable": true,
              "sort": "none",
              "sortable": true,
              "strictWidth": false,
              "style": {
                "classes": ""
              },
              "toggleSwitch": {
                "color": {
                  "selected": "",
                  "unselected": ""
                }
              },
              "viewParams": {},
              "viewPath": "",
              "visible": false,
              "width": ""
            },
            {
              "align": "center",
              "boolean": "checkbox",
              "dateFormat": "MM/DD/YYYY",
              "editable": false,
              "field": "",
              "filter": {
                "boolean": {
                  "condition": ""
                },
                "date": {
                  "condition": "",
                  "value": ""
                },
                "enabled": false,
                "number": {
                  "condition": "",
                  "value": ""
                },
                "string": {
                  "condition": "",
                  "value": ""
                },
                "visible": "on-hover"
              },
              "footer": {
                "align": "center",
                "justify": "left",
                "style": {
                  "classes": ""
                },
                "title": ""
              },
              "header": {
                "align": "center",
                "justify": "left",
                "style": {
                  "classes": ""
                },
                "title": ""
              },
              "justify": "auto",
              "nullFormat": {
                "includeNullStrings": false,
                "nullFormatValue": "",
                "strict": false
              },
              "number": "value",
              "numberFormat": "0,0.##",
              "progressBar": {
                "bar": {
                  "color": "",
                  "style": {
                    "classes": ""
                  }
                },
                "max": 100,
                "min": 0,
                "track": {
                  "color": "",
                  "style": {
                    "classes": ""
                  }
                },
                "value": {
                  "enabled": true,
                  "format": "0,0.##",
                  "justify": "center",
                  "style": {
                    "classes": ""
                  }
                }
              },
              "render": "auto",
              "resizable": true,
              "sort": "none",
              "sortable": true,
              "strictWidth": false,
              "style": {
                "classes": ""
              },
              "toggleSwitch": {
                "color": {
                  "selected": "",
                  "unselected": ""
                }
              },
              "viewParams": {},
              "viewPath": "",
              "visible": false,
              "width": ""
            },
            {
              "align": "center",
              "boolean": "checkbox",
              "dateFormat": "MM/DD/YYYY",
              "editable": false,
              "field": "",
              "filter": {
                "boolean": {
                  "condition": ""
                },
                "date": {
                  "condition": "",
                  "value": ""
                },
                "enabled": false,
                "number": {
                  "condition": "",
                  "value": ""
                },
                "string": {
                  "condition": "",
                  "value": ""
                },
                "visible": "on-hover"
              },
              "footer": {
                "align": "center",
                "justify": "left",
                "style": {
                  "classes": ""
                },
                "title": ""
              },
              "header": {
                "align": "center",
                "justify": "left",
                "style": {
                  "classes": ""
                },
                "title": ""
              },
              "justify": "auto",
              "nullFormat": {
                "includeNullStrings": false,
                "nullFormatValue": "",
                "strict": false
              },
              "number": "value",
              "numberFormat": "0,0.##",
              "progressBar": {
                "bar": {
                  "color": "",
                  "style": {
                    "classes": ""
                  }
                },
                "max": 100,
                "min": 0,
                "track": {
                  "color": "",
                  "style": {
                    "classes": ""
                  }
                },
                "value": {
                  "enabled": true,
                  "format": "0,0.##",
                  "justify": "center",
                  "style": {
                    "classes": ""
                  }
                }
              },
              "render": "auto",
              "resizable": true,
              "sort": "none",
              "sortable": true,
              "strictWidth": false,
              "style": {
                "classes": ""
              },
              "toggleSwitch": {
                "color": {
                  "selected": "",
                  "unselected": ""
                }
              },
              "viewParams": {},
              "viewPath": "",
              "visible": false,
              "width": ""
            },
            {
              "align": "center",
              "boolean": "checkbox",
              "dateFormat": "MM/DD/YYYY",
              "editable": false,
              "field": "",
              "filter": {
                "boolean": {
                  "condition": ""
                },
                "date": {
                  "condition": "",
                  "value": ""
                },
                "enabled": false,
                "number": {
                  "condition": "",
                  "value": ""
                },
                "string": {
                  "condition": "",
                  "value": ""
                },
                "visible": "on-hover"
              },
              "footer": {
                "align": "center",
                "justify": "left",
                "style": {
                  "classes": ""
                },
                "title": ""
              },
              "header": {
                "align": "center",
                "justify": "left",
                "style": {
                  "classes": ""
                },
                "title": ""
              },
              "justify": "auto",
              "nullFormat": {
                "includeNullStrings": false,
                "nullFormatValue": "",
                "strict": false
              },
              "number": "value",
              "numberFormat": "0,0.##",
              "progressBar": {
                "bar": {
                  "color": "",
                  "style": {
                    "classes": ""
                  }
                },
                "max": 100,
                "min": 0,
                "track": {
                  "color": "",
                  "style": {
                    "classes": ""
                  }
                },
                "value": {
                  "enabled": true,
                  "format": "0,0.##",
                  "justify": "center",
                  "style": {
                    "classes": ""
                  }
                }
              },
              "render": "auto",
              "resizable": true,
              "sort": "none",
              "sortable": true,
              "strictWidth": false,
              "style": {
                "classes": ""
              },
              "toggleSwitch": {
                "color": {
                  "selected": "",
                  "unselected": ""
                }
              },
              "viewParams": {},
              "viewPath": "",
              "visible": false,
              "width": ""
            },
            {
              "align": "center",
              "boolean": "checkbox",
              "dateFormat": "MM/DD/YYYY",
              "editable": false,
              "field": "",
              "filter": {
                "boolean": {
                  "condition": ""
                },
                "date": {
                  "condition": "",
                  "value": ""
                },
                "enabled": false,
                "number": {
                  "condition": "",
                  "value": ""
                },
                "string": {
                  "condition": "",
                  "value": ""
                },
                "visible": "on-hover"
              },
              "footer": {
                "align": "center",
                "justify": "left",
                "style": {
                  "classes": ""
                },
                "title": ""
              },
              "header": {
                "align": "center",
                "justify": "left",
                "style": {
                  "classes": ""
                },
                "title": ""
              },
              "justify": "auto",
              "nullFormat": {
                "includeNullStrings": false,
                "nullFormatValue": "",
                "strict": false
              },
              "number": "value",
              "numberFormat": "0,0.##",
              "progressBar": {
                "bar": {
                  "color": "",
                  "style": {
                    "classes": ""
                  }
                },
                "max": 100,
                "min": 0,
                "track": {
                  "color": "",
                  "style": {
                    "classes": ""
                  }
                },
                "value": {
                  "enabled": true,
                  "format": "0,0.##",
                  "justify": "center",
                  "style": {
                    "classes": ""
                  }
                }
              },
              "render": "auto",
              "resizable": true,
              "sort": "none",
              "sortable": true,
              "strictWidth": false,
              "style": {
                "classes": ""
              },
              "toggleSwitch": {
                "color": {
                  "selected": "",
                  "unselected": ""
                }
              },
              "viewParams": {},
              "viewPath": "",
              "visible": false,
              "width": ""
            },
            {
              "align": "center",
              "boolean": "checkbox",
              "dateFormat": "MM/DD/YYYY",
              "editable": false,
              "field": "",
              "filter": {
                "boolean": {
                  "condition": ""
                },
                "date": {
                  "condition": "",
                  "value": ""
                },
                "enabled": false,
                "number": {
                  "condition": "",
                  "value": ""
                },
                "string": {
                  "condition": "",
                  "value": ""
                },
                "visible": "on-hover"
              },
              "footer": {
                "align": "center",
                "justify": "left",
                "style": {
                  "classes": ""
                },
                "title": ""
              },
              "header": {
                "align": "center",
                "justify": "left",
                "style": {
                  "classes": ""
                },
                "title": ""
              },
              "justify": "auto",
              "nullFormat": {
                "includeNullStrings": false,
                "nullFormatValue": "",
                "strict": false
              },
              "number": "value",
              "numberFormat": "0,0.##",
              "progressBar": {
                "bar": {
                  "color": "",
                  "style": {
                    "classes": ""
                  }
                },
                "max": 100,
                "min": 0,
                "track": {
                  "color": "",
                  "style": {
                    "classes": ""
                  }
                },
                "value": {
                  "enabled": true,
                  "format": "0,0.##",
                  "justify": "center",
                  "style": {
                    "classes": ""
                  }
                }
              },
              "render": "auto",
              "resizable": true,
              "sort": "none",
              "sortable": true,
              "strictWidth": false,
              "style": {
                "classes": ""
              },
              "toggleSwitch": {
                "color": {
                  "selected": "",
                  "unselected": ""
                }
              },
              "viewParams": {},
              "viewPath": "",
              "visible": false,
              "width": ""
            },
            {
              "align": "center",
              "boolean": "checkbox",
              "dateFormat": "MM/DD/YYYY",
              "editable": false,
              "field": "",
              "filter": {
                "boolean": {
                  "condition": ""
                },
                "date": {
                  "condition": "",
                  "value": ""
                },
                "enabled": false,
                "number": {
                  "condition": "",
                  "value": ""
                },
                "string": {
                  "condition": "",
                  "value": ""
                },
                "visible": "on-hover"
              },
              "footer": {
                "align": "center",
                "justify": "left",
                "style": {
                  "classes": ""
                },
                "title": ""
              },
              "header": {
                "align": "center",
                "justify": "left",
                "style": {
                  "classes": ""
                },
                "title": ""
              },
              "justify": "auto",
              "nullFormat": {
                "includeNullStrings": false,
                "nullFormatValue": "",
                "strict": false
              },
              "number": "value",
              "numberFormat": "0,0.##",
              "progressBar": {
                "bar": {
                  "color": "",
                  "style": {
                    "classes": ""
                  }
                },
                "max": 100,
                "min": 0,
                "track": {
                  "color": "",
                  "style": {
                    "classes": ""
                  }
                },
                "value": {
                  "enabled": true,
                  "format": "0,0.##",
                  "justify": "center",
                  "style": {
                    "classes": ""
                  }
                }
              },
              "render": "auto",
              "resizable": true,
              "sort": "none",
              "sortable": true,
              "strictWidth": false,
              "style": {
                "classes": ""
              },
              "toggleSwitch": {
                "color": {
                  "selected": "",
                  "unselected": ""
                }
              },
              "viewParams": {},
              "viewPath": "",
              "visible": false,
              "width": ""
            },
            {
              "align": "center",
              "boolean": "checkbox",
              "dateFormat": "MM/DD/YYYY",
              "editable": false,
              "field": "",
              "filter": {
                "boolean": {
                  "condition": ""
                },
                "date": {
                  "condition": "",
                  "value": ""
                },
                "enabled": false,
                "number": {
                  "condition": "",
                  "value": ""
                },
                "string": {
                  "condition": "",
                  "value": ""
                },
                "visible": "on-hover"
              },
              "footer": {
                "align": "center",
                "justify": "left",
                "style": {
                  "classes": ""
                },
                "title": ""
              },
              "header": {
                "align": "center",
                "justify": "left",
                "style": {
                  "classes": ""
                },
                "title": ""
              },
              "justify": "auto",
              "nullFormat": {
                "includeNullStrings": false,
                "nullFormatValue": "",
                "strict": false
              },
              "number": "value",
              "numberFormat": "0,0.##",
              "progressBar": {
                "bar": {
                  "color": "",
                  "style": {
                    "classes": ""
                  }
                },
                "max": 100,
                "min": 0,
                "track": {
                  "color": "",
                  "style": {
                    "classes": ""
                  }
                },
                "value": {
                  "enabled": true,
                  "format": "0,0.##",
                  "justify": "center",
                  "style": {
                    "classes": ""
                  }
                }
              },
              "render": "auto",
              "resizable": true,
              "sort": "none",
              "sortable": true,
              "strictWidth": false,
              "style": {
                "classes": ""
              },
              "toggleSwitch": {
                "color": {
                  "selected": "",
                  "unselected": ""
                }
              },
              "viewParams": {},
              "viewPath": "",
              "visible": false,
              "width": ""
            },
            {
              "align": "center",
              "boolean": "checkbox",
              "dateFormat": "MM/DD/YYYY",
              "editable": false,
              "field": "",
              "filter": {
                "boolean": {
                  "condition": ""
                },
                "date": {
                  "condition": "",
                  "value": ""
                },
                "enabled": false,
                "number": {
                  "condition": "",
                  "value": ""
                },
                "string": {
                  "condition": "",
                  "value": ""
                },
                "visible": "on-hover"
              },
              "footer": {
                "align": "center",
                "justify": "left",
                "style": {
                  "classes": ""
                },
                "title": ""
              },
              "header": {
                "align": "center",
                "justify": "left",
                "style": {
                  "classes": ""
                },
                "title": ""
              },
              "justify": "auto",
              "nullFormat": {
                "includeNullStrings": false,
                "nullFormatValue": "",
                "strict": false
              },
              "number": "value",
              "numberFormat": "0,0.##",
              "progressBar": {
                "bar": {
                  "color": "",
                  "style": {
                    "classes": ""
                  }
                },
                "max": 100,
                "min": 0,
                "track": {
                  "color": "",
                  "style": {
                    "classes": ""
                  }
                },
                "value": {
                  "enabled": true,
                  "format": "0,0.##",
                  "justify": "center",
                  "style": {
                    "classes": ""
                  }
                }
              },
              "render": "auto",
              "resizable": true,
              "sort": "none",
              "sortable": true,
              "strictWidth": false,
              "style": {
                "classes": ""
              },
              "toggleSwitch": {
                "color": {
                  "selected": "",
                  "unselected": ""
                }
              },
              "viewParams": {},
              "viewPath": "",
              "visible": false,
              "width": ""
            },
            {
              "align": "center",
              "boolean": "checkbox",
              "dateFormat": "MM/DD/YYYY",
              "editable": false,
              "field": "",
              "filter": {
                "boolean": {
                  "condition": ""
                },
                "date": {
                  "condition": "",
                  "value": ""
                },
                "enabled": false,
                "number": {
                  "condition": "",
                  "value": ""
                },
                "string": {
                  "condition": "",
                  "value": ""
                },
                "visible": "on-hover"
              },
              "footer": {
                "align": "center",
                "justify": "left",
                "style": {
                  "classes": ""
                },
                "title": ""
              },
              "header": {
                "align": "center",
                "justify": "left",
                "style": {
                  "classes": ""
                },
                "title": ""
              },
              "justify": "auto",
              "nullFormat": {
                "includeNullStrings": false,
                "nullFormatValue": "",
                "strict": false
              },
              "number": "value",
              "numberFormat": "0,0.##",
              "progressBar": {
                "bar": {
                  "color": "",
                  "style": {
                    "classes": ""
                  }
                },
                "max": 100,
                "min": 0,
                "track": {
                  "color": "",
                  "style": {
                    "classes": ""
                  }
                },
                "value": {
                  "enabled": true,
                  "format": "0,0.##",
                  "justify": "center",
                  "style": {
                    "classes": ""
                  }
                }
              },
              "render": "auto",
              "resizable": true,
              "sort": "none",
              "sortable": true,
              "strictWidth": false,
              "style": {
                "classes": ""
              },
              "toggleSwitch": {
                "color": {
                  "selected": "",
                  "unselected": ""
                }
              },
              "viewParams": {},
              "viewPath": "",
              "visible": false,
              "width": ""
            },
            {
              "align": "center",
              "boolean": "checkbox",
              "dateFormat": "MM/DD/YYYY",
              "editable": false,
              "field": "",
              "filter": {
                "boolean": {
                  "condition": ""
                },
                "date": {
                  "condition": "",
                  "value": ""
                },
                "enabled": false,
                "number": {
                  "condition": "",
                  "value": ""
                },
                "string": {
                  "condition": "",
                  "value": ""
                },
                "visible": "on-hover"
              },
              "footer": {
                "align": "center",
                "justify": "left",
                "style": {
                  "classes": ""
                },
                "title": ""
              },
              "header": {
                "align": "center",
                "justify": "left",
                "style": {
                  "classes": ""
                },
                "title": ""
              },
              "justify": "auto",
              "nullFormat": {
                "includeNullStrings": false,
                "nullFormatValue": "",
                "strict": false
              },
              "number": "value",
              "numberFormat": "0,0.##",
              "progressBar": {
                "bar": {
                  "color": "",
                  "style": {
                    "classes": ""
                  }
                },
                "max": 100,
                "min": 0,
                "track": {
                  "color": "",
                  "style": {
                    "classes": ""
                  }
                },
                "value": {
                  "enabled": true,
                  "format": "0,0.##",
                  "justify": "center",
                  "style": {
                    "classes": ""
                  }
                }
              },
              "render": "auto",
              "resizable": true,
              "sort": "none",
              "sortable": true,
              "strictWidth": false,
              "style": {
                "classes": ""
              },
              "toggleSwitch": {
                "color": {
                  "selected": "",
                  "unselected": ""
                }
              },
              "viewParams": {},
              "viewPath": "",
              "visible": false,
              "width": ""
            },
            {
              "align": "center",
              "boolean": "checkbox",
              "dateFormat": "MM/DD/YYYY",
              "editable": false,
              "field": "",
              "filter": {
                "boolean": {
                  "condition": ""
                },
                "date": {
                  "condition": "",
                  "value": ""
                },
                "enabled": false,
                "number": {
                  "condition": "",
                  "value": ""
                },
                "string": {
                  "condition": "",
                  "value": ""
                },
                "visible": "on-hover"
              },
              "footer": {
                "align": "center",
                "justify": "left",
                "style": {
                  "classes": ""
                },
                "title": ""
              },
              "header": {
                "align": "center",
                "justify": "left",
                "style": {
                  "classes": ""
                },
                "title": ""
              },
              "justify": "auto",
              "nullFormat": {
                "includeNullStrings": false,
                "nullFormatValue": "",
                "strict": false
              },
              "number": "value",
              "numberFormat": "0,0.##",
              "progressBar": {
                "bar": {
                  "color": "",
                  "style": {
                    "classes": ""
                  }
                },
                "max": 100,
                "min": 0,
                "track": {
                  "color": "",
                  "style": {
                    "classes": ""
                  }
                },
                "value": {
                  "enabled": true,
                  "format": "0,0.##",
                  "justify": "center",
                  "style": {
                    "classes": ""
                  }
                }
              },
              "render": "auto",
              "resizable": true,
              "sort": "none",
              "sortable": true,
              "strictWidth": false,
              "style": {
                "classes": ""
              },
              "toggleSwitch": {
                "color": {
                  "selected": "",
                  "unselected": ""
                }
              },
              "viewParams": {},
              "viewPath": "",
              "visible": false,
              "width": ""
            },
            {
              "align": "center",
              "boolean": "checkbox",
              "dateFormat": "MM/DD/YYYY",
              "editable": false,
              "field": "",
              "filter": {
                "boolean": {
                  "condition": ""
                },
                "date": {
                  "condition": "",
                  "value": ""
                },
                "enabled": false,
                "number": {
                  "condition": "",
                  "value": ""
                },
                "string": {
                  "condition": "",
                  "value": ""
                },
                "visible": "on-hover"
              },
              "footer": {
                "align": "center",
                "justify": "left",
                "style": {
                  "classes": ""
                },
                "title": ""
              },
              "header": {
                "align": "center",
                "justify": "left",
                "style": {
                  "classes": ""
                },
                "title": ""
              },
              "justify": "auto",
              "nullFormat": {
                "includeNullStrings": false,
                "nullFormatValue": "",
                "strict": false
              },
              "number": "value",
              "numberFormat": "0,0.##",
              "progressBar": {
                "bar": {
                  "color": "",
                  "style": {
                    "classes": ""
                  }
                },
                "max": 100,
                "min": 0,
                "track": {
                  "color": "",
                  "style": {
                    "classes": ""
                  }
                },
                "value": {
                  "enabled": true,
                  "format": "0,0.##",
                  "justify": "center",
                  "style": {
                    "classes": ""
                  }
                }
              },
              "render": "auto",
              "resizable": true,
              "sort": "none",
              "sortable": true,
              "strictWidth": false,
              "style": {
                "classes": ""
              },
              "toggleSwitch": {
                "color": {
                  "selected": "",
                  "unselected": ""
                }
              },
              "viewParams": {},
              "viewPath": "",
              "visible": false,
              "width": ""
            },
            {
              "align": "center",
              "boolean": "checkbox",
              "dateFormat": "MM/DD/YYYY",
              "editable": false,
              "field": "",
              "filter": {
                "boolean": {
                  "condition": ""
                },
                "date": {
                  "condition": "",
                  "value": ""
                },
                "enabled": false,
                "number": {
                  "condition": "",
                  "value": ""
                },
                "string": {
                  "condition": "",
                  "value": ""
                },
                "visible": "on-hover"
              },
              "footer": {
                "align": "center",
                "justify": "left",
                "style": {
                  "classes": ""
                },
                "title": ""
              },
              "header": {
                "align": "center",
                "justify": "left",
                "style": {
                  "classes": ""
                },
                "title": ""
              },
              "justify": "auto",
              "nullFormat": {
                "includeNullStrings": false,
                "nullFormatValue": "",
                "strict": false
              },
              "number": "value",
              "numberFormat": "0,0.##",
              "progressBar": {
                "bar": {
                  "color": "",
                  "style": {
                    "classes": ""
                  }
                },
                "max": 100,
                "min": 0,
                "track": {
                  "color": "",
                  "style": {
                    "classes": ""
                  }
                },
                "value": {
                  "enabled": true,
                  "format": "0,0.##",
                  "justify": "center",
                  "style": {
                    "classes": ""
                  }
                }
              },
              "render": "auto",
              "resizable": true,
              "sort": "none",
              "sortable": true,
              "strictWidth": false,
              "style": {
                "classes": ""
              },
              "toggleSwitch": {
                "color": {
                  "selected": "",
                  "unselected": ""
                }
              },
              "viewParams": {},
              "viewPath": "",
              "visible": false,
              "width": ""
            },
            {
              "align": "center",
              "boolean": "checkbox",
              "dateFormat": "MM/DD/YYYY",
              "editable": false,
              "field": "",
              "filter": {
                "boolean": {
                  "condition": ""
                },
                "date": {
                  "condition": "",
                  "value": ""
                },
                "enabled": false,
                "number": {
                  "condition": "",
                  "value": ""
                },
                "string": {
                  "condition": "",
                  "value": ""
                },
                "visible": "on-hover"
              },
              "footer": {
                "align": "center",
                "justify": "left",
                "style": {
                  "classes": ""
                },
                "title": ""
              },
              "header": {
                "align": "center",
                "justify": "left",
                "style": {
                  "classes": ""
                },
                "title": ""
              },
              "justify": "auto",
              "nullFormat": {
                "includeNullStrings": false,
                "nullFormatValue": "",
                "strict": false
              },
              "number": "value",
              "numberFormat": "0,0.##",
              "progressBar": {
                "bar": {
                  "color": "",
                  "style": {
                    "classes": ""
                  }
                },
                "max": 100,
                "min": 0,
                "track": {
                  "color": "",
                  "style": {
                    "classes": ""
                  }
                },
                "value": {
                  "enabled": true,
                  "format": "0,0.##",
                  "justify": "center",
                  "style": {
                    "classes": ""
                  }
                }
              },
              "render": "auto",
              "resizable": true,
              "sort": "none",
              "sortable": true,
              "strictWidth": false,
              "style": {
                "classes": ""
              },
              "toggleSwitch": {
                "color": {
                  "selected": "",
                  "unselected": ""
                }
              },
              "viewParams": {},
              "viewPath": "",
              "visible": false,
              "width": ""
            }
          ],
          "dragOrderable": false,
          "emptyMessage": {
            "noData": {
              "text": "Please select a different site from the dropdown list, or add a new CIP system."
            }
          },
          "filter": {
            "enabled": true
          },
          "style": {
            "marginLeft": 4,
            "marginRight": 4
          },
          "virtualized": false
        },
        "scripts": {
          "customMethods": [],
          "extensionFunctions": null,
          "messageHandlers": [
            {
              "messageType": "update_bindings",
              "pageScope": true,
              "script": "\tself.refreshBinding(\"props.data\")\n",
              "sessionScope": false,
              "viewScope": false
            }
          ]
        },
        "type": "ia.display.table"
      }
    ],
    "meta": {
      "name": "root"
    },
    "props": {
      "direction": "column"
    },
    "type": "ia.container.flex"
  }
}